kpindex/GetKp.py
kpindex/Globals.py
kpindex/ReadKp.py
kpindex/UpdateLocalData.py
kpindex/_CompareUpdates.py
kpindex/_ConvertFTPFile.py
kpindex/_DeleteFTPFile.py
kpindex/_DownloadFTPFile.py
kpindex/_DownloadFTPIndex.py
kpindex/_ParseFTP.py
kpindex/_ReadDataIndex.py
kpindex/_ReadKPTab.py
kpindex/_ReadKpTxt.py
kpindex/_UpdateDataIndex.py
kpindex/__init__.py
kpindex-2.1.0.dist-info/licenses/LICENSE
kpindex-2.1.0.dist-info/METADATA
kpindex-2.1.0.dist-info/WHEEL
kpindex-2.1.0.dist-info/top_level.txt
kpindex-2.1.0.dist-info/RECORD
