Metadata-Version: 2.4
Name: kpindex
Version: 2.1.0
Summary: Very simple package for obtaining the kp index data
Home-page: https://github.com/mattkjames7/kpindex
Author: Matthew Knight James
Author-email: mattkjames7@gmail.com
Classifier: Programming Language :: Python :: 3
Classifier: License :: OSI Approved :: MIT License
Classifier: Operating System :: POSIX
Classifier: Operating System :: MacOS :: MacOS X
Classifier: Operating System :: Microsoft :: Windows
License-File: LICENSE
Requires-Dist: numpy
Requires-Dist: RecarrayTools
Requires-Dist: PyFileIO
Requires-Dist: DateTimeTools
Dynamic: author
Dynamic: author-email
Dynamic: classifier
Dynamic: description
Dynamic: description-content-type
Dynamic: home-page
Dynamic: license-file
Dynamic: requires-dist
Dynamic: summary
